CHANGES.txt
LICENSE.txt
MANIFEST.in
README.txt
setup.py
Flask_Scss.egg-info/PKG-INFO
Flask_Scss.egg-info/SOURCES.txt
Flask_Scss.egg-info/dependency_links.txt
Flask_Scss.egg-info/namespace_packages.txt
Flask_Scss.egg-info/not-zip-safe
Flask_Scss.egg-info/requires.txt
Flask_Scss.egg-info/top_level.txt
flaskext/__init__.py
flaskext/flask_scss.py
flaskext/test/__init__.py
flaskext/test/test_scss.py