Metadata-Version: 1.0
Name: Flask-Scss
Version: 0.1
Summary: Adds support for scss files to Flask applications
Home-page: https://bitbucket.org/aerdhyl/flask-scss
Author: Bruno Carlin
Author-email: self@aerdhyl.eu
License: MIT
Platform: any
Classifier: Development Status :: 4 - Beta
Classifier: Environment :: Web Environment
Classifier: Intended Audience :: Developers
Classifier: License :: OSI Approved :: MIT License
Classifier: Operating System :: OS Independent
Classifier: Programming Language :: Python
Classifier: Topic :: Internet :: WWW/HTTP :: Dynamic Content
Classifier: Topic :: Software Development :: Libraries :: Python Modules
